fastq_remove_duplicate_qname
