Metadata-Version: 1.1
Name: fastq-remove-duplicate-qname
Version: 0.2
Summary: remove duplicate QNAME from a fastq
Home-page: https://github.com/jeremiahsavage/fastq_remove_duplicate_qname/
Author: Jeremiah H. Savage
Author-email: jeremiahsavage@gmail.com
License: Apache 2.0
Platform: UNKNOWN
Classifier: Development Status :: 3 - Alpha
Classifier: Intended Audience :: Developers
Classifier: License :: OSI Approved :: Apache Software License
Classifier: Programming Language :: Python
Classifier: Programming Language :: Python :: 2
Classifier: Programming Language :: Python :: 3
